steganograph/__init__.py
steganograph/src/__init__.py
steganograph/src/steganograph.py
steganograph/src/utils.py
steganograph/test/__init__.py
steganograph/test/test_steganograph.py
steganograph-0.0.14.dist-info/LICENSE
steganograph-0.0.14.dist-info/METADATA
steganograph-0.0.14.dist-info/WHEEL
steganograph-0.0.14.dist-info/top_level.txt
steganograph-0.0.14.dist-info/RECORD
