Metadata-Version: 2.1
Name: steganograph
Version: 0.0.14
Summary: Head a file in img and extracted without chnaging the image size and you can protect your file with a password
Home-page: https://github.com/bouz1/PypiContributions/tree/main/steganography
Author: Abb BOZZ
Author-email: bozzabb1@gmail.com
License: MIT
Platform: UNKNOWN
Classifier: License :: OSI Approved :: MIT License
Classifier: Programming Language :: Python :: 3.10
Classifier: Operating System :: OS Independent
Requires-Python: >=3.7
License-File: LICENSE
Provides-Extra: dev
Requires-Dist: hashlib ; extra == 'dev'
Requires-Dist: imageio ; extra == 'dev'
Requires-Dist: numpy ; extra == 'dev'
Requires-Dist: os ; extra == 'dev'
Requires-Dist: re ; extra == 'dev'
